model_transfer/__init__.py
model_transfer/neuro_persistence_sdk.py
neuroedge_model_transfer-1.0.0.dist-info/licenses/LICENSE.lic
neuroedge_model_transfer-1.0.0.dist-info/METADATA
neuroedge_model_transfer-1.0.0.dist-info/WHEEL
neuroedge_model_transfer-1.0.0.dist-info/top_level.txt
neuroedge_model_transfer-1.0.0.dist-info/RECORD
