Metadata-Version: 2.4
Name: neuroedge_model_transfer
Version: 1.0.0
Summary: A package to read a file from a given location and upload it to an S3 bucket
Author: Radhika Menon
Author-email: Radhika.Menon@cognizant.com
Classifier: Programming Language :: Python :: 3
Classifier: License :: OSI Approved :: MIT License
Classifier: Operating System :: OS Independent
Requires-Python: >=3.6
License-File: LICENSE.lic
Requires-Dist: boto3>=1.18.0
Dynamic: author
Dynamic: author-email
Dynamic: classifier
Dynamic: license-file
Dynamic: requires-dist
Dynamic: requires-python
Dynamic: summary
